ejercicio2/ej02.v
module FF_D1(input wire clock, reset, enable, d, output reg Y);
  always @ (posedge clock or posedge reset or posedge enable) begin
    if(reset) begin
      Y <= 1'b0;
    end
    else if (enable) begin
      Y <= d;
    end
  end
endmodule


module ALU(input wire [3:0] A, B, input wire [2:0] S, output reg [3:0] R, output reg [1:0] C_Z);//implementacion de la ALU

  reg [4:0] result;
  // parametros tabla 5.1 libro
  parameter ST = 3'd0;
  parameter COMPI = 3'd1;
  parameter LIT = 3'd2;
  parameter ADDI = 3'd3;
  parameter NANDI = 3'd4;

  always @(*) begin// operaciones a realizar con la ALU con un switch case
    case(S)
    ST:
       result <= A;

    COMPI:
       result <= (A - B);

    LIT:
       result <= B;

    ADDI:
       result <= (A + B);

    NANDI:
       result <= (A ~& B);

    default: result <= 5'd0;
    endcase

    assign {R, C_Z[0], C_Z[1]} = {result[3:0], result[4], ((result[3:0]==4'b0) ? 1'b1 : 1'b0) };

  end

endmodule


module Accumulator(input wire clk, reset, enable, input wire [3:0] D, output wire [3:0] Accu) ;
  FF_D1 FF1(clk, reset, enable, D[3], Accu[3]);
  FF_D1 FF2(clk, reset, enable, D[2], Accu[2]);
  FF_D1 FF3(clk, reset, enable, D[1], Accu[1]);
  FF_D1 FF4(clk, reset, enable, D[0], Accu[0]);
endmodule


module Bus_Driver(input wire enable, input wire [3:0] bus, output wire [3:0] Y);

  assign Y = enable ? bus : 4'bz;

endmodule


module Control (input wire clk, reset, enable1, enable2, enable3, input wire [3:0] bus, input wire [2:0] S,
  output wire [3:0] Y, output wire [1:0] C_Z);

  wire [3:0] accu, R, data_bus;

  Bus_Driver BD1(enable2, bus, data_bus);
  Accumulator Accu1(clk, reset, enable1, R, accu);
  ALU alu1(accu, data_bus, S, R, C_Z);
  Bus_Driver BD2(enable3, R, Y);

endmodule

ejercicio2/ej02_tb.v
module testbench();
reg clock, reset, enable1, enable2, enable3;
reg [3:0] bus;
reg [2:0] s;
wire [3:0] Y;
wire [1:0] C_Z;


always//instanciacion del clock
  begin
    clock <= 1;
    #1 clock <= ~clock;// se realiza el cambio del reloj
    #1;
end


Control ctrl1(clock, reset, enable1, enable2, enable3, bus, s, Y, C_Z);


initial begin// test del programa
  $display("Ejercicio 2\n");
  $display("CLK Reset | Enable1  Enable2  Enable3 | Bus      S   | Y    C_Z");
  $display("----------|---------------------------|--------------|----------");
  $monitor("%b     %b   |   %b         %b         %b   | %b    %b  | %b  %b", clock,reset,enable1,enable2,enable3,bus,s,Y,C_Z);
  reset = 1;
  #2 enable1 = 0;  enable2 = 0; enable3 = 0; reset = 0; bus = 4'd4; s = 3'd0;
  #2 enable1 = 1;  enable2 = 1; enable3 = 1; 
  #2 bus = 4'd8; #2 s = 3'd2;
  #2 bus = 4'd7; #2 s = 3'd1;
  #2 s = 3'd0;
  #2 bus = 4'd3; #2 s = 3'd4;
  #2 bus = 4'd15; #2 s = 3'd3;

  $finish;
end

initial begin//ejecutar GTKWave para diagramas de timing.
  $dumpfile("ej02_tb.vcd");
  $dumpvars(0, testbench);
end

endmodule

ejercicio2/ej02_tb.vcd
$date
	Sat Nov 07 23:04:35 2020
$end
$version
	Icarus Verilog
$end
$timescale
	1ps
$end
$scope module testbench $end
$var wire 4 ! Y [3:0] $end
$var wire 2 " C_Z [1:0] $end
$var reg 4 # bus [3:0] $end
$var reg 1 $ clock $end
$var reg 1 % enable1 $end
$var reg 1 & enable2 $end
$var reg 1 ' enable3 $end
$var reg 1 ( reset $end
$var reg 3 ) s [2:0] $end
$scope module ctrl1 $end
$var wire 3 * S [2:0] $end
$var wire 4 + bus [3:0] $end
$var wire 1 $ clk $end
$var wire 1 % enable1 $end
$var wire 1 & enable2 $end
$var wire 1 ' enable3 $end
$var wire 1 ( reset $end
$var wire 4 , data_bus [3:0] $end
$var wire 4 - accu [3:0] $end
$var wire 4 . Y [3:0] $end
$var wire 4 / R [3:0] $end
$var wire 2 0 C_Z [1:0] $end
$scope module Accu1 $end
$var wire 1 $ clk $end
$var wire 1 % enable $end
$var wire 1 ( reset $end
$var wire 4 1 D [3:0] $end
$var wire 4 2 Accu [3:0] $end
$scope module FF1 $end
$var wire 1 $ clock $end
$var wire 1 3 d $end
$var wire 1 % enable $end
$var wire 1 ( reset $end
$var reg 1 4 Y $end
$upscope $end
$scope module FF2 $end
$var wire 1 $ clock $end
$var wire 1 5 d $end
$var wire 1 % enable $end
$var wire 1 ( reset $end
$var reg 1 6 Y $end
$upscope $end
$scope module FF3 $end
$var wire 1 $ clock $end
$var wire 1 7 d $end
$var wire 1 % enable $end
$var wire 1 ( reset $end
$var reg 1 8 Y $end
$upscope $end
$scope module FF4 $end
$var wire 1 $ clock $end
$var wire 1 9 d $end
$var wire 1 % enable $end
$var wire 1 ( reset $end
$var reg 1 : Y $end
$upscope $end
$upscope $end
$scope module BD1 $end
$var wire 4 ; bus [3:0] $end
$var wire 1 & enable $end
$var wire 4 < Y [3:0] $end
$upscope $end
$scope module BD2 $end
$var wire 1 ' enable $end
$var wire 4 = bus [3:0] $end
$var wire 4 > Y [3:0] $end
$upscope $end
$scope module alu1 $end
$var wire 4 ? A [3:0] $end
$var wire 4 @ B [3:0] $end
$var wire 3 A S [2:0] $end
$var reg 2 B C_Z [1:0] $end
$var reg 4 C R [3:0] $end
$var reg 5 D result [4:0] $end
$upscope $end
$upscope $end
$upscope $end
$enddefinitions $end
#0
$dumpvars
b0 D
bx C
bx B
bx A
bx @
b0 ?
bx >
bx =
bx <
bx ;
0:
x9
08
x7
06
x5
04
x3
b0 2
bx 1
bx 0
bx /
bx .
b0 -
bx ,
bx +
bx *
bx )
1(
x'
x&
x%
1$
bx #
bx "
bx !
$end
#1
0$
#2
1$
09
07
05
03
b0 /
b0 1
b0 =
b0 C
b10 "
b10 0
b10 B
bz !
bz .
bz >
bz ,
bz <
bz @
b0 )
b0 *
b0 A
b100 #
b100 +
b100 ;
0(
0'
0&
0%
#3
0$
#4
1$
b0 !
b0 .
b0 >
b100 ,
b100 <
b100 @
1'
1&
1%
#5
0$
#6
1$
b1000 ,
b1000 <
b1000 @
b1000 #
b1000 +
b1000 ;
#7
0$
#8
b1000 D
1$
b10 )
b10 *
b10 A
#9
0$
#10
19
17
15
b1000 -
b1000 2
b1000 ?
14
b111 D
1$
b111 !
b111 .
b111 >
03
b111 /
b111 1
b111 =
b111 C
b0 "
b0 0
b0 B
b111 ,
b111 <
b111 @
b111 #
b111 +
b111 ;
#11
0$
#12
b1 !
b1 .
b1 >
07
05
b1 /
b1 1
b1 =
b1 C
04
16
18
b111 -
b111 2
b111 ?
1:
b0 D
1$
b1 )
b1 *
b1 A
#13
0$
#14
17
15
0:
08
b0 -
b0 2
b0 ?
06
b0 D
1$
b111 !
b111 .
b111 >
19
b111 /
b111 1
b111 =
b111 C
b0 "
b0 0
b0 B
b0 )
b0 *
b0 A
#15
0$
#16
1$
b0 !
b0 .
b0 >
09
07
05
b0 /
b0 1
b0 =
b0 C
b10 "
b10 0
b10 B
b11 ,
b11 <
b11 @
b11 #
b11 +
b11 ;
#17
0$
#18
b11111 D
1$
b100 )
b100 *
b100 A
#19
0$
#20
b10000 D
14
16
18
b1111 -
b1111 2
b1111 ?
1:
1$
b1111 !
b1111 .
b1111 >
19
17
15
13
b1111 /
b1111 1
b1111 =
b1111 C
b1 "
b1 0
b1 B
b1111 ,
b1111 <
b1111 @
b1111 #
b1111 +
b1111 ;
#21
0$
#22
0:
08
06
b0 -
b0 2
b0 ?
04
b1111 D
1$
b1110 !
b1110 .
b1110 >
09
17
15
13
b1110 /
b1110 1
b1110 =
b1110 C
b1 "
b1 0
b1 B
b11 )
b11 *
b11 A
