ejercicio1/ej01.v
module FF_1BIT(input wire clk, reset, enable, D, output reg Y) ;
  always @(posedge clk or posedge enable or posedge reset) begin
    if (reset)  Y <= 1'b0;
    else if(enable) Y <= D;
  end
endmodule//FF de 1 bit

module Program_Couter(input wire clk, reset, enable, load, input [11:0] loadPC, output reg[11:0] count);
//contador de 12 bits con entradas de clock, reset, enable y load

  always @ (posedge clk or posedge reset or posedge enable or posedge load) begin
    if(reset) begin
     count <= 12'd0; // si se resetea empieza en cero
    end
    else if(clk & enable & ~load) begin
        #2 count <= count + 12'd1; // si esta en enable cuenta el contador sino no cuenta
    end
    else if(clk & load & enable) begin
        #2 count <= loadPC; //precargando el valor
    end
  end

endmodule// program couter implementado con un contador de 12 bits

module Fetch (input wire clk, reset, enable, input wire [7:0] program_byte, output wire [3:0] instr, oprnd) ;
  FF_1BIT FF1(clk, reset, enable, program_byte[7], instr[3]);
  FF_1BIT FF2(clk, reset, enable, program_byte[6], instr[2]);
  FF_1BIT FF3(clk, reset, enable, program_byte[5], instr[1]);
  FF_1BIT FF4(clk, reset, enable, program_byte[4], instr[0]);
  FF_1BIT FF5(clk, reset, enable, program_byte[3], oprnd[3]);
  FF_1BIT FF6(clk, reset, enable, program_byte[2], oprnd[2]);
  FF_1BIT FF7(clk, reset, enable, program_byte[1], oprnd[1]);
  FF_1BIT FF8(clk, reset, enable, program_byte[0], oprnd[0]);
endmodule//fetch el cual es un fliflop de 8 bits implementado con el ff tipo d de 1 bit

module Program_ROM (input wire [11:0] address, output wire [7:0] word);//memoria rom
  reg [7:0] mem [0:4095];// creacion de arreglo de memoria
  initial begin
      $readmemb("memory.list", mem);//lectura del archivo de datos
  end
  assign word = mem[address];// resultado leido de la memoria
endmodule//program rom implementada junto con una lista de datos en el memory list

module Control (input clk, resetC, resetF, enableC, enableF, load, input [11:0] loadPC, output [3:0] instr, oprnd);

wire [11:0] PC;
wire [7:0] program_byte;

Program_Couter PC1(clk, resetC, enableC, load, loadPC, PC);
Program_ROM PR1(PC, program_byte);
Fetch F1(clk, resetF, enableF, program_byte, instr, oprnd);

endmodule//union de todos modulos para el fragmento del microprocesador .

ejercicio1/ej01_tb.v
module testbench();
reg clock, resetC, resetF, enableC, enableF, load;//variables para el contador
reg [11:0] loadPC;
wire [3:0] instr;
wire [3:0] oprnd;


always//instanciacion del clock
  begin
    clock <= 1;
    #1 clock <= ~clock;// se realiza el cambio del reloj
    #1;
end


Control ctrl1(clock, resetC, resetF, enableC, enableF, load, loadPC, instr, oprnd);


initial begin// test del programa
  $display("Ejercicio 1\n");
  $display("CLK ResetC ResetF| EnableC  EnableF  Load | instr oprnd");
  $display("-----------------|------------------------|--------------");
  $monitor("%b     %b      %b   |  %b         %b        %b  | %b   %b", clock,resetC,resetF,enableC,enableF,load,instr,oprnd);
  resetC = 1; resetF = 1;
  #2 enableF = 0;  enableC = 0; resetC = 0; resetF = 0; load = 0; loadPC = 12'd0;
  #2; #2;
  #2 enableC = 1;  enableF = 1;
  #2; #2; #2; #2; #2;
  #2 load = 1; loadPC = 12'd12;
  #2 load = 0;
  #2; #2; #2;
  $finish;
end


initial begin//ejecutar GTKWave para diagramas de timing.
  $dumpfile("ej01_tb.vcd");
  $dumpvars(0, testbench);
end

endmodule

ejercicio1/ej01_tb.vcd
$date
	Sat Nov 07 23:11:53 2020
$end
$version
	Icarus Verilog
$end
$timescale
	1ps
$end
$scope module testbench $end
$var wire 4 ! oprnd [3:0] $end
$var wire 4 " instr [3:0] $end
$var reg 1 # clock $end
$var reg 1 $ enableC $end
$var reg 1 % enableF $end
$var reg 1 & load $end
$var reg 12 ' loadPC [11:0] $end
$var reg 1 ( resetC $end
$var reg 1 ) resetF $end
$scope module ctrl1 $end
$var wire 1 # clk $end
$var wire 1 $ enableC $end
$var wire 1 % enableF $end
$var wire 1 & load $end
$var wire 12 * loadPC [11:0] $end
$var wire 1 ( resetC $end
$var wire 1 ) resetF $end
$var wire 8 + program_byte [7:0] $end
$var wire 4 , oprnd [3:0] $end
$var wire 4 - instr [3:0] $end
$var wire 12 . PC [11:0] $end
$scope module F1 $end
$var wire 1 # clk $end
$var wire 1 % enable $end
$var wire 1 ) reset $end
$var wire 8 / program_byte [7:0] $end
$var wire 4 0 oprnd [3:0] $end
$var wire 4 1 instr [3:0] $end
$scope module FF1 $end
$var wire 1 2 D $end
$var wire 1 # clk $end
$var wire 1 % enable $end
$var wire 1 ) reset $end
$var reg 1 3 Y $end
$upscope $end
$scope module FF2 $end
$var wire 1 4 D $end
$var wire 1 # clk $end
$var wire 1 % enable $end
$var wire 1 ) reset $end
$var reg 1 5 Y $end
$upscope $end
$scope module FF3 $end
$var wire 1 6 D $end
$var wire 1 # clk $end
$var wire 1 % enable $end
$var wire 1 ) reset $end
$var reg 1 7 Y $end
$upscope $end
$scope module FF4 $end
$var wire 1 8 D $end
$var wire 1 # clk $end
$var wire 1 % enable $end
$var wire 1 ) reset $end
$var reg 1 9 Y $end
$upscope $end
$scope module FF5 $end
$var wire 1 : D $end
$var wire 1 # clk $end
$var wire 1 % enable $end
$var wire 1 ) reset $end
$var reg 1 ; Y $end
$upscope $end
$scope module FF6 $end
$var wire 1 < D $end
$var wire 1 # clk $end
$var wire 1 % enable $end
$var wire 1 ) reset $end
$var reg 1 = Y $end
$upscope $end
$scope module FF7 $end
$var wire 1 > D $end
$var wire 1 # clk $end
$var wire 1 % enable $end
$var wire 1 ) reset $end
$var reg 1 ? Y $end
$upscope $end
$scope module FF8 $end
$var wire 1 @ D $end
$var wire 1 # clk $end
$var wire 1 % enable $end
$var wire 1 ) reset $end
$var reg 1 A Y $end
$upscope $end
$upscope $end
$scope module PC1 $end
$var wire 1 # clk $end
$var wire 1 $ enable $end
$var wire 1 & load $end
$var wire 12 B loadPC [11:0] $end
$var wire 1 ( reset $end
$var reg 12 C count [11:0] $end
$upscope $end
$scope module PR1 $end
$var wire 12 D address [11:0] $end
$var wire 8 E word [7:0] $end
$upscope $end
$upscope $end
$upscope $end
$enddefinitions $end
#0
$dumpvars
b11101101 E
b0 D
b0 C
bx B
0A
1@
0?
0>
0=
1<
0;
1:
09
08
07
16
05
14
03
12
b0 1
b0 0
b11101101 /
b0 .
b0 -
b0 ,
b11101101 +
bx *
1)
1(
bx '
x&
x%
x$
1#
b0 "
b0 !
$end
#1
0#
#2
1#
b0 '
b0 *
b0 B
0&
0)
0(
0$
0%
#3
0#
#4
1#
#5
0#
#6
1#
#7
0#
#8
1A
1=
b1101 !
b1101 ,
b1101 0
1;
17
15
b1110 "
b1110 -
b1110 1
13
1#
1%
1$
#9
0#
#10
0A
1?
0=
b10 !
b10 ,
b10 0
0;
19
07
05
b1 "
b1 -
b1 1
03
0@
1>
0<
0:
18
06
04
02
1#
b10010 +
b10010 /
b10010 E
b1 .
b1 C
b1 D
#11
0#
#12
13
15
b1111 "
b1111 -
b1111 1
17
1=
b111 !
b111 ,
b111 0
1A
1@
1<
16
14
12
1#
b11110111 +
b11110111 /
b11110111 E
b10 .
b10 C
b10 D
#13
0#
#14
1#
b11 .
b11 C
b11 D
#15
0#
#16
05
07
b1000 "
b1000 -
b1000 1
09
b11 !
b11 ,
b11 0
0=
0<
08
06
04
1#
b10000011 +
b10000011 /
b10000011 E
b100 .
b100 C
b100 D
#17
0#
#18
b1 !
b1 ,
b1 0
0?
b1100 "
b1100 -
b1100 1
15
0>
14
1#
b11000001 +
b11000001 /
b11000001 E
b101 .
b101 C
b101 D
#19
0#
#20
03
05
17
b11 "
b11 -
b11 1
19
1=
b111 !
b111 ,
b111 0
1?
1>
1<
18
16
04
02
1#
b110111 +
b110111 /
b110111 E
b110 .
b110 C
b110 D
b1100 '
b1100 *
b1100 B
1&
#21
0#
#22
b101 !
b101 ,
b101 0
0?
09
b1010 "
b1010 -
b1010 1
13
0>
08
12
1#
b10100101 +
b10100101 /
b10100101 E
b1100 .
b1100 C
b1100 D
0&
#23
0#
#24
03
b0 "
b0 -
b0 1
07
b111 !
b111 ,
b111 0
1?
1>
06
02
1#
b111 +
b111 /
b111 E
b1101 .
b1101 C
b1101 D
#25
0#
#26
b11 !
b11 ,
b11 0
0=
17
b110 "
b110 -
b110 1
15
0<
16
14
1#
b1100011 +
b1100011 /
b1100011 E
b1110 .
b1110 C
b1110 D
#27
0#
#28
b1110 "
b1110 -
b1110 1
13
1;
b1001 !
b1001 ,
b1001 0
0?
0>
1:
12
1#
b11101001 +
b11101001 /
b11101001 E
b1111 .
b1111 C
b1111 D
